mockwalkers/__init__.py
mockwalkers/geometry.py
mockwalkers/graphic.py
mockwalkers/obstacle.py
mockwalkers/solver.py
mockwalkers/vdcalculator.py
mockwalkers/walkers.py
mockwalkers-0.0.0.dist-info/LICENSE
mockwalkers-0.0.0.dist-info/METADATA
mockwalkers-0.0.0.dist-info/WHEEL
mockwalkers-0.0.0.dist-info/top_level.txt
mockwalkers-0.0.0.dist-info/RECORD
