Metadata-Version: 2.1
Name: mockwalkers
Version: 0.0.0
Summary: A walkers dynamic simulation library.
Author: Alouette, David, Jimoh, Matias
License: GNU GENERAL PUBLIC LICENSE
Project-URL: Homepage, https://github.com/matiassimon/mockwalkers
Keywords: walker,dynamic,crowd
Classifier: License :: OSI Approved :: MIT License
Classifier: Programming Language :: Python
Classifier: Programming Language :: Python :: 3
Requires-Python: >=3.9
License-File: LICENSE
Requires-Dist: numpy
Requires-Dist: matplotlib
Requires-Dist: multimethod
Provides-Extra: dev
Requires-Dist: black ; extra == 'dev'
Requires-Dist: pytest ; extra == 'dev'
Requires-Dist: sphinx ; extra == 'dev'
Requires-Dist: furo ; extra == 'dev'
Requires-Dist: build ; extra == 'dev'
Requires-Dist: twine ; extra == 'dev'
